{"schemaVersion":"2.0","unrealEngineVersion":"5.4.4-35576357+++UE5+Release-5.4","name":"ALS_Gait","path":"/Game/AdditionalContents/AdvancedLocomotionV4/Data/Enums/ALS_Gait.ALS_Gait","assetType":"Enum","unrealClass":"UserDefinedEnum","values":[{"index":0,"value":0,"name":"NewEnumerator0","authoredName":"Walking","displayName":"Walking","hidden":false},{"index":1,"value":1,"name":"NewEnumerator1","authoredName":"Running","displayName":"Running","hidden":false},{"index":2,"value":2,"name":"NewEnumerator2","authoredName":"Sprinting","displayName":"Sprinting","hidden":false},{"index":3,"value":3,"name":"ALS_MAX","authoredName":"ALS_MAX","displayName":"ALS MAX","hidden":false}],"dependencies":[],"relations":[]}