{
	"assetKey": "Game_AdditionalContents_AdvancedLocomotionV4_Blueprints_AnimNotifys_CameraShake_Notify",
	"graph": "Received_Notify",
	"entryName": "Received Notify",
	"entryNodeGuid": "16EAF510452B6944985562B3311397A7",
	"nodes": [
		{
			"nodeGuid": "16EAF510452B6944985562B3311397A7",
			"class": "K2Node_FunctionEntry",
			"title": "Received Notify",
			"comment": "",
			"x": 0,
			"y": 0,
			"memberName": "",
			"functionName": "",
			"variableName": "",
			"targetClass": "",
			"pins": [
				{
					"pinId": "95F8F40C4C349E2086F5488C4849CB0B",
					"name": "then",
					"direction": "Output",
					"type": "exec",
					"defaultValue": ""
				},
				{
					"pinId": "CE963A4C4DE67D07C9CF58AEB9FDC9D2",
					"name": "MeshComp",
					"direction": "Output",
					"type": "object|/Script/Engine.SkeletalMeshComponent",
					"defaultValue": ""
				},
				{
					"pinId": "BF2985A74432F1EA187D4AA1E2DCEBA3",
					"name": "Animation",
					"direction": "Output",
					"type": "object|/Script/Engine.AnimSequenceBase",
					"defaultValue": ""
				},
				{
					"pinId": "7A7AA2444867FE1647EDAD9D66765A6F",
					"name": "EventReference",
					"direction": "Output",
					"type": "struct|/Script/Engine.AnimNotifyEventReference|ref|const",
					"defaultValue": ""
				}
			]
		},
		{
			"nodeGuid": "758C4ABE4F16030D8E81D2A07B0831B5",
			"class": "K2Node_FunctionResult",
			"title": "Nodo di restituzione",
			"comment": "",
			"x": 1920,
			"y": 0,
			"memberName": "",
			"functionName": "",
			"variableName": "",
			"targetClass": "",
			"pins": [
				{
					"pinId": "9E8ABA2A4210A7975DC7B4BEDC288921",
					"name": "execute",
					"direction": "Input",
					"type": "exec",
					"defaultValue": ""
				},
				{
					"pinId": "BCF199F74596A45D5789278992D0B8C0",
					"name": "ReturnValue",
					"direction": "Input",
					"type": "bool",
					"defaultValue": "false"
				}
			]
		},
		{
			"nodeGuid": "105CC9ED4F041029AB8455A0C1388F3E",
			"class": "K2Node_CallFunction",
			"title": "Get Owner\nLa destinazione è Actor Component",
			"comment": "",
			"x": 176,
			"y": 48,
			"memberName": "",
			"functionName": "",
			"variableName": "",
			"targetClass": "",
			"pins": [
				{
					"pinId": "36BD0183444D0BA150DC4A932830C9F3",
					"name": "self",
					"direction": "Input",
					"type": "object|/Script/Engine.ActorComponent",
					"defaultValue": ""
				},
				{
					"pinId": "D1233616498DF49851CADFB063A3E534",
					"name": "ReturnValue",
					"direction": "Output",
					"type": "object|/Script/Engine.Actor",
					"defaultValue": ""
				}
			]
		},
		{
			"nodeGuid": "D8429B344B3DB5F034EA7EB39F8B6C9B",
			"class": "K2Node_VariableGet",
			"title": "Get ShakeClass",
			"comment": "",
			"x": 1440,
			"y": 128,
			"memberName": "",
			"functionName": "",
			"variableName": "",
			"targetClass": "",
			"pins": [
				{
					"pinId": "A22E41B54D352AF92134D2AC66D35509",
					"name": "ShakeClass",
					"direction": "Output",
					"type": "class|/Script/GameplayCameras.LegacyCameraShake",
					"defaultValue": ""
				},
				{
					"pinId": "770DD52D427CCC1873E4BEBD0DBA8A4A",
					"name": "self",
					"direction": "Input",
					"type": "object|/Game/AdditionalContents/AdvancedLocomotionV4/Blueprints/AnimNotifys/CameraShake_Notify.CameraShake_Notify_C",
					"defaultValue": ""
				}
			]
		},
		{
			"nodeGuid": "7DBA1C2E45B80D96A2B9A6BD52B15EDE",
			"class": "K2Node_VariableGet",
			"title": "Get Scale",
			"comment": "",
			"x": 1440,
			"y": 176,
			"memberName": "",
			"functionName": "",
			"variableName": "",
			"targetClass": "",
			"pins": [
				{
					"pinId": "06E3F99349FA4AC73995AE9EC77AE4C9",
					"name": "Scale",
					"direction": "Output",
					"type": "real|double",
					"defaultValue": "0.0"
				},
				{
					"pinId": "8366FC8B497D1A874CBACEAB0DBE6EB9",
					"name": "self",
					"direction": "Input",
					"type": "object|/Game/AdditionalContents/AdvancedLocomotionV4/Blueprints/AnimNotifys/CameraShake_Notify.CameraShake_Notify_C",
					"defaultValue": ""
				}
			]
		},
		{
			"nodeGuid": "F14D61714D5D2FB1ADC668B44CF9567B",
			"class": "K2Node_CallFunction",
			"title": "Client Start Camera Shake\nLa destinazione è Player Controller\nReplicato sul client proprietario (se server)",
			"comment": "",
			"x": 1632,
			"y": -32,
			"memberName": "",
			"functionName": "",
			"variableName": "",
			"targetClass": "",
			"pins": [
				{
					"pinId": "6DBD04964FF87BD82A542FA494F8EC0A",
					"name": "execute",
					"direction": "Input",
					"type": "exec",
					"defaultValue": ""
				},
				{
					"pinId": "7C8D593F44D80D998E9388B5B170C96F",
					"name": "then",
					"direction": "Output",
					"type": "exec",
					"defaultValue": ""
				},
				{
					"pinId": "669FE93644674FB5C31CF6A4F912AD38",
					"name": "self",
					"direction": "Input",
					"type": "object|/Script/Engine.PlayerController",
					"defaultValue": ""
				},
				{
					"pinId": "BB291C9048398D4BB3F4AA9CA59935ED",
					"name": "Shake",
					"direction": "Input",
					"type": "class|/Script/Engine.CameraShakeBase",
					"defaultValue": ""
				},
				{
					"pinId": "C4048FD049C5698BAC8B16852F9C876C",
					"name": "Scale",
					"direction": "Input",
					"type": "real|float",
					"defaultValue": "1.000000"
				},
				{
					"pinId": "9CE7E5534F4E4EBD9AD7E184A6B43A4F",
					"name": "PlaySpace",
					"direction": "Input",
					"type": "byte|/Script/Engine.ECameraShakePlaySpace",
					"defaultValue": "CameraLocal"
				},
				{
					"pinId": "BF56D09444C6B57A3E0AD2B60388DB5D",
					"name": "UserPlaySpaceRot",
					"direction": "Input",
					"type": "struct|/Script/CoreUObject.Rotator",
					"defaultValue": "0, 0, 0"
				}
			]
		},
		{
			"nodeGuid": "02005EEC4BC03C83CD9B4E9D15F55FEE",
			"class": "K2Node_DynamicCast",
			"title": "Cast To PlayerController",
			"comment": "",
			"x": 1344,
			"y": 0,
			"memberName": "",
			"functionName": "",
			"variableName": "",
			"targetClass": "",
			"pins": [
				{
					"pinId": "802A3E0445350B61BE1564BED56CE435",
					"name": "execute",
					"direction": "Input",
					"type": "exec",
					"defaultValue": ""
				},
				{
					"pinId": "1A0AAB0143A668EC3D2BF2A5098CB45B",
					"name": "then",
					"direction": "Output",
					"type": "exec",
					"defaultValue": ""
				},
				{
					"pinId": "4D476A0F4D284BE7737094971F1320A8",
					"name": "CastFailed",
					"direction": "Output",
					"type": "exec",
					"defaultValue": ""
				},
				{
					"pinId": "87529DFA469CE69E56B8EFA5FC0E6A2A",
					"name": "Object",
					"direction": "Input",
					"type": "object|/Script/CoreUObject.Object",
					"defaultValue": ""
				},
				{
					"pinId": "358C80A94A6E1B5BE4A1BCB0E8179320",
					"name": "AsPlayer Controller",
					"direction": "Output",
					"type": "object|/Script/Engine.PlayerController",
					"defaultValue": ""
				},
				{
					"pinId": "14C216FD48878F49942898870491327D",
					"name": "bSuccess",
					"direction": "Output",
					"type": "bool",
					"defaultValue": ""
				}
			]
		},
		{
			"nodeGuid": "3D5089564856841C37EB7CBC126900DE",
			"class": "K2Node_MacroInstance",
			"title": "Is Valid",
			"comment": "",
			"x": 416,
			"y": 0,
			"memberName": "",
			"functionName": "",
			"variableName": "",
			"targetClass": "",
			"pins": [
				{
					"pinId": "4B58C5904314E87E4A748A86F1BA165D",
					"name": "exec",
					"direction": "Input",
					"type": "exec",
					"defaultValue": ""
				},
				{
					"pinId": "9C2D664B4C4820B802EE7B816F163D4E",
					"name": "InputObject",
					"direction": "Input",
					"type": "object|/Script/CoreUObject.Object",
					"defaultValue": ""
				},
				{
					"pinId": "6BE08CFC4F2C183EE80F19831FE8F073",
					"name": "Is Valid",
					"direction": "Output",
					"type": "exec",
					"defaultValue": ""
				},
				{
					"pinId": "DFC3B7EC4FD91FFDD349C48D068C6E26",
					"name": "Is Not Valid",
					"direction": "Output",
					"type": "exec",
					"defaultValue": ""
				}
			]
		},
		{
			"nodeGuid": "A920BF3941351265648963A1B6E782FC",
			"class": "K2Node_DynamicCast",
			"title": "Cast To Pawn",
			"comment": "",
			"x": 672,
			"y": 0,
			"memberName": "",
			"functionName": "",
			"variableName": "",
			"targetClass": "",
			"pins": [
				{
					"pinId": "CA449C6A4A78B9C0748557A787E7404D",
					"name": "execute",
					"direction": "Input",
					"type": "exec",
					"defaultValue": ""
				},
				{
					"pinId": "50543BA6445517FEF801F2B0FE8C43CA",
					"name": "then",
					"direction": "Output",
					"type": "exec",
					"defaultValue": ""
				},
				{
					"pinId": "AF52C87E42C5ED61BCC3EEA970D395F8",
					"name": "CastFailed",
					"direction": "Output",
					"type": "exec",
					"defaultValue": ""
				},
				{
					"pinId": "489A9F1B4C0AEB6407863884C66E6060",
					"name": "Object",
					"direction": "Input",
					"type": "object|/Script/CoreUObject.Object",
					"defaultValue": ""
				},
				{
					"pinId": "9E56CACE47F0F0C59E9D19868218773A",
					"name": "AsPedina",
					"direction": "Output",
					"type": "object|/Script/Engine.Pawn",
					"defaultValue": ""
				},
				{
					"pinId": "C01C062946B013830A9A06982CD4BFD8",
					"name": "bSuccess",
					"direction": "Output",
					"type": "bool",
					"defaultValue": ""
				}
			]
		},
		{
			"nodeGuid": "6762803E46BD7697C210EDA56378E73E",
			"class": "K2Node_CallFunction",
			"title": "Get Controller\nLa destinazione è Pedina",
			"comment": "",
			"x": 880,
			"y": 64,
			"memberName": "",
			"functionName": "",
			"variableName": "",
			"targetClass": "",
			"pins": [
				{
					"pinId": "A03E9B94494E7E548FC17187D56585A7",
					"name": "self",
					"direction": "Input",
					"type": "object|/Script/Engine.Pawn",
					"defaultValue": ""
				},
				{
					"pinId": "7E51FF4E46EA4FD77B26B3A414E99D5F",
					"name": "ReturnValue",
					"direction": "Output",
					"type": "object|/Script/Engine.Controller",
					"defaultValue": ""
				}
			]
		},
		{
			"nodeGuid": "17899382467E6BAC61B4F8AC887FE90B",
			"class": "K2Node_MacroInstance",
			"title": "Is Valid",
			"comment": "",
			"x": 1104,
			"y": 0,
			"memberName": "",
			"functionName": "",
			"variableName": "",
			"targetClass": "",
			"pins": [
				{
					"pinId": "19D43E4749ADCA8B22625DA8974B34B2",
					"name": "exec",
					"direction": "Input",
					"type": "exec",
					"defaultValue": ""
				},
				{
					"pinId": "104BF8524FFD344B5AF6C8A545E70ECD",
					"name": "InputObject",
					"direction": "Input",
					"type": "object|/Script/CoreUObject.Object",
					"defaultValue": ""
				},
				{
					"pinId": "1006B7CE4D9CF3C84FC17DA075FB0BF0",
					"name": "Is Valid",
					"direction": "Output",
					"type": "exec",
					"defaultValue": ""
				},
				{
					"pinId": "C1063BF14BFFA5199EAE1A8FFB1FB3F4",
					"name": "Is Not Valid",
					"direction": "Output",
					"type": "exec",
					"defaultValue": ""
				}
			]
		}
	],
	"edges": [
		{
			"assetKey": "Game_AdditionalContents_AdvancedLocomotionV4_Blueprints_AnimNotifys_CameraShake_Notify",
			"graph": "Received_Notify",
			"edgeType": "exec",
			"fromNodeGuid": "16EAF510452B6944985562B3311397A7",
			"fromPinId": "95F8F40C4C349E2086F5488C4849CB0B",
			"fromPinName": "then",
			"toNodeGuid": "3D5089564856841C37EB7CBC126900DE",
			"toPinId": "4B58C5904314E87E4A748A86F1BA165D",
			"toPinName": "exec"
		},
		{
			"assetKey": "Game_AdditionalContents_AdvancedLocomotionV4_Blueprints_AnimNotifys_CameraShake_Notify",
			"graph": "Received_Notify",
			"edgeType": "data",
			"fromNodeGuid": "16EAF510452B6944985562B3311397A7",
			"fromPinId": "CE963A4C4DE67D07C9CF58AEB9FDC9D2",
			"fromPinName": "MeshComp",
			"toNodeGuid": "105CC9ED4F041029AB8455A0C1388F3E",
			"toPinId": "36BD0183444D0BA150DC4A932830C9F3",
			"toPinName": "self"
		},
		{
			"assetKey": "Game_AdditionalContents_AdvancedLocomotionV4_Blueprints_AnimNotifys_CameraShake_Notify",
			"graph": "Received_Notify",
			"edgeType": "exec",
			"fromNodeGuid": "F14D61714D5D2FB1ADC668B44CF9567B",
			"fromPinId": "7C8D593F44D80D998E9388B5B170C96F",
			"fromPinName": "then",
			"toNodeGuid": "758C4ABE4F16030D8E81D2A07B0831B5",
			"toPinId": "9E8ABA2A4210A7975DC7B4BEDC288921",
			"toPinName": "execute"
		},
		{
			"assetKey": "Game_AdditionalContents_AdvancedLocomotionV4_Blueprints_AnimNotifys_CameraShake_Notify",
			"graph": "Received_Notify",
			"edgeType": "data",
			"fromNodeGuid": "105CC9ED4F041029AB8455A0C1388F3E",
			"fromPinId": "D1233616498DF49851CADFB063A3E534",
			"fromPinName": "ReturnValue",
			"toNodeGuid": "3D5089564856841C37EB7CBC126900DE",
			"toPinId": "9C2D664B4C4820B802EE7B816F163D4E",
			"toPinName": "InputObject"
		},
		{
			"assetKey": "Game_AdditionalContents_AdvancedLocomotionV4_Blueprints_AnimNotifys_CameraShake_Notify",
			"graph": "Received_Notify",
			"edgeType": "data",
			"fromNodeGuid": "105CC9ED4F041029AB8455A0C1388F3E",
			"fromPinId": "D1233616498DF49851CADFB063A3E534",
			"fromPinName": "ReturnValue",
			"toNodeGuid": "A920BF3941351265648963A1B6E782FC",
			"toPinId": "489A9F1B4C0AEB6407863884C66E6060",
			"toPinName": "Object"
		},
		{
			"assetKey": "Game_AdditionalContents_AdvancedLocomotionV4_Blueprints_AnimNotifys_CameraShake_Notify",
			"graph": "Received_Notify",
			"edgeType": "data",
			"fromNodeGuid": "D8429B344B3DB5F034EA7EB39F8B6C9B",
			"fromPinId": "A22E41B54D352AF92134D2AC66D35509",
			"fromPinName": "ShakeClass",
			"toNodeGuid": "F14D61714D5D2FB1ADC668B44CF9567B",
			"toPinId": "BB291C9048398D4BB3F4AA9CA59935ED",
			"toPinName": "Shake"
		},
		{
			"assetKey": "Game_AdditionalContents_AdvancedLocomotionV4_Blueprints_AnimNotifys_CameraShake_Notify",
			"graph": "Received_Notify",
			"edgeType": "data",
			"fromNodeGuid": "7DBA1C2E45B80D96A2B9A6BD52B15EDE",
			"fromPinId": "06E3F99349FA4AC73995AE9EC77AE4C9",
			"fromPinName": "Scale",
			"toNodeGuid": "F14D61714D5D2FB1ADC668B44CF9567B",
			"toPinId": "C4048FD049C5698BAC8B16852F9C876C",
			"toPinName": "Scale"
		},
		{
			"assetKey": "Game_AdditionalContents_AdvancedLocomotionV4_Blueprints_AnimNotifys_CameraShake_Notify",
			"graph": "Received_Notify",
			"edgeType": "exec",
			"fromNodeGuid": "02005EEC4BC03C83CD9B4E9D15F55FEE",
			"fromPinId": "1A0AAB0143A668EC3D2BF2A5098CB45B",
			"fromPinName": "then",
			"toNodeGuid": "F14D61714D5D2FB1ADC668B44CF9567B",
			"toPinId": "6DBD04964FF87BD82A542FA494F8EC0A",
			"toPinName": "execute"
		},
		{
			"assetKey": "Game_AdditionalContents_AdvancedLocomotionV4_Blueprints_AnimNotifys_CameraShake_Notify",
			"graph": "Received_Notify",
			"edgeType": "data",
			"fromNodeGuid": "02005EEC4BC03C83CD9B4E9D15F55FEE",
			"fromPinId": "358C80A94A6E1B5BE4A1BCB0E8179320",
			"fromPinName": "AsPlayer Controller",
			"toNodeGuid": "F14D61714D5D2FB1ADC668B44CF9567B",
			"toPinId": "669FE93644674FB5C31CF6A4F912AD38",
			"toPinName": "self"
		},
		{
			"assetKey": "Game_AdditionalContents_AdvancedLocomotionV4_Blueprints_AnimNotifys_CameraShake_Notify",
			"graph": "Received_Notify",
			"edgeType": "exec",
			"fromNodeGuid": "17899382467E6BAC61B4F8AC887FE90B",
			"fromPinId": "1006B7CE4D9CF3C84FC17DA075FB0BF0",
			"fromPinName": "Is Valid",
			"toNodeGuid": "02005EEC4BC03C83CD9B4E9D15F55FEE",
			"toPinId": "802A3E0445350B61BE1564BED56CE435",
			"toPinName": "execute"
		},
		{
			"assetKey": "Game_AdditionalContents_AdvancedLocomotionV4_Blueprints_AnimNotifys_CameraShake_Notify",
			"graph": "Received_Notify",
			"edgeType": "data",
			"fromNodeGuid": "6762803E46BD7697C210EDA56378E73E",
			"fromPinId": "7E51FF4E46EA4FD77B26B3A414E99D5F",
			"fromPinName": "ReturnValue",
			"toNodeGuid": "02005EEC4BC03C83CD9B4E9D15F55FEE",
			"toPinId": "87529DFA469CE69E56B8EFA5FC0E6A2A",
			"toPinName": "Object"
		},
		{
			"assetKey": "Game_AdditionalContents_AdvancedLocomotionV4_Blueprints_AnimNotifys_CameraShake_Notify",
			"graph": "Received_Notify",
			"edgeType": "exec",
			"fromNodeGuid": "3D5089564856841C37EB7CBC126900DE",
			"fromPinId": "6BE08CFC4F2C183EE80F19831FE8F073",
			"fromPinName": "Is Valid",
			"toNodeGuid": "A920BF3941351265648963A1B6E782FC",
			"toPinId": "CA449C6A4A78B9C0748557A787E7404D",
			"toPinName": "execute"
		},
		{
			"assetKey": "Game_AdditionalContents_AdvancedLocomotionV4_Blueprints_AnimNotifys_CameraShake_Notify",
			"graph": "Received_Notify",
			"edgeType": "exec",
			"fromNodeGuid": "A920BF3941351265648963A1B6E782FC",
			"fromPinId": "50543BA6445517FEF801F2B0FE8C43CA",
			"fromPinName": "then",
			"toNodeGuid": "17899382467E6BAC61B4F8AC887FE90B",
			"toPinId": "19D43E4749ADCA8B22625DA8974B34B2",
			"toPinName": "exec"
		},
		{
			"assetKey": "Game_AdditionalContents_AdvancedLocomotionV4_Blueprints_AnimNotifys_CameraShake_Notify",
			"graph": "Received_Notify",
			"edgeType": "data",
			"fromNodeGuid": "A920BF3941351265648963A1B6E782FC",
			"fromPinId": "9E56CACE47F0F0C59E9D19868218773A",
			"fromPinName": "AsPedina",
			"toNodeGuid": "6762803E46BD7697C210EDA56378E73E",
			"toPinId": "A03E9B94494E7E548FC17187D56585A7",
			"toPinName": "self"
		},
		{
			"assetKey": "Game_AdditionalContents_AdvancedLocomotionV4_Blueprints_AnimNotifys_CameraShake_Notify",
			"graph": "Received_Notify",
			"edgeType": "data",
			"fromNodeGuid": "6762803E46BD7697C210EDA56378E73E",
			"fromPinId": "7E51FF4E46EA4FD77B26B3A414E99D5F",
			"fromPinName": "ReturnValue",
			"toNodeGuid": "17899382467E6BAC61B4F8AC887FE90B",
			"toPinId": "104BF8524FFD344B5AF6C8A545E70ECD",
			"toPinName": "InputObject"
		}
	],
	"variablesRead": [
		"Get Scale",
		"Get ShakeClass"
	],
	"variablesWritten": [],
	"functionsCalled": [
		"Client Start Camera Shake\nLa destinazione è Player Controller\nReplicato sul client proprietario (se server)",
		"Get Controller\nLa destinazione è Pedina",
		"Get Owner\nLa destinazione è Actor Component"
	],
	"widgetsTouched": [],
	"componentsTouched": [],
	"externalBlueprintReferences": [
		"Cast To Pawn",
		"Cast To PlayerController",
		"Client Start Camera Shake\nLa destinazione è Player Controller\nReplicato sul client proprietario (se server)",
		"Get Controller\nLa destinazione è Pedina",
		"Get Owner\nLa destinazione è Actor Component"
	],
	"flowId": "F001",
	"graphId": "G001",
	"assetName": "CameraShake_Notify",
	"assetPath": "/Game/AdditionalContents/AdvancedLocomotionV4/Blueprints/AnimNotifys/CameraShake_Notify.CameraShake_Notify"
}