{
	"assetKey": "Game_AdditionalContents_AdvancedLocomotionV4_Blueprints_GameModes_ALS_GameMode_SP",
	"graph": "UserConstructionScript",
	"entryName": "Construction Script",
	"entryNodeGuid": "4886C62844386452A09DDAB2912CB307",
	"nodes": [
		{
			"nodeGuid": "4886C62844386452A09DDAB2912CB307",
			"class": "K2Node_FunctionEntry",
			"title": "Construction Script",
			"comment": "",
			"x": 0,
			"y": 0,
			"memberName": "",
			"functionName": "",
			"variableName": "",
			"targetClass": "",
			"pins": [
				{
					"pinId": "7544179D49A8DF80617631B81B82CBA2",
					"name": "then",
					"direction": "Output",
					"type": "exec",
					"defaultValue": ""
				}
			]
		}
	],
	"edges": [],
	"variablesRead": [],
	"variablesWritten": [],
	"functionsCalled": [],
	"widgetsTouched": [],
	"componentsTouched": [],
	"externalBlueprintReferences": [],
	"flowId": "F001",
	"graphId": "G002",
	"assetName": "ALS_GameMode_SP",
	"assetPath": "/Game/AdditionalContents/AdvancedLocomotionV4/Blueprints/GameModes/ALS_GameMode_SP.ALS_GameMode_SP"
}