{
	"assetKey": "Game_ChuckContent_UI_WIDGET_MENU_1_MENU_ARCHIVE_Equipment_WBP_SelectorButton",
	"graph": "EventGraph",
	"entryName": "Evento On Removed from Focus Path",
	"entryNodeGuid": "3D457EE5452141D1D92B729E025FB00F",
	"nodes": [
		{
			"nodeGuid": "9A1F535A4C046FC809050A87C2BB6C4D",
			"class": "K2Node_Event",
			"title": "Evento Construct",
			"comment": "",
			"x": -48,
			"y": 272,
			"memberName": "",
			"functionName": "",
			"variableName": "",
			"targetClass": "",
			"pins": [
				{
					"pinId": "0EB6536E40E0F98D38DD969A56923775",
					"name": "OutputDelegate",
					"direction": "Output",
					"type": "delegate",
					"defaultValue": ""
				},
				{
					"pinId": "37BB92294B2E6EC6DB85D1BC7E7D69A4",
					"name": "then",
					"direction": "Output",
					"type": "exec",
					"defaultValue": ""
				}
			]
		},
		{
			"nodeGuid": "678F9A75450022669630FBBAB239A734",
			"class": "K2Node_VariableGet",
			"title": "Get Txt_ItemName",
			"comment": "",
			"x": 128,
			"y": 359,
			"memberName": "",
			"functionName": "",
			"variableName": "",
			"targetClass": "",
			"pins": [
				{
					"pinId": "CF50978A4B4ED96D02057C88C8D02509",
					"name": "Txt_ItemName",
					"direction": "Output",
					"type": "text",
					"defaultValue": ""
				},
				{
					"pinId": "0687109944EB098113454F96658DB80E",
					"name": "self",
					"direction": "Input",
					"type": "object|/Game/ChuckContent/UI/WIDGET_MENU/1_MENU_ARCHIVE/Equipment/WBP_SelectorButton.WBP_SelectorButton_C",
					"defaultValue": ""
				}
			]
		},
		{
			"nodeGuid": "02EDC53B461F614D5C04E98FA83BB160",
			"class": "K2Node_CallFunction",
			"title": "SetText (Text)\nLa destinazione è Testo",
			"comment": "",
			"x": 288,
			"y": 258,
			"memberName": "",
			"functionName": "",
			"variableName": "",
			"targetClass": "",
			"pins": [
				{
					"pinId": "03406C0F480FE622A4F78480951934A8",
					"name": "execute",
					"direction": "Input",
					"type": "exec",
					"defaultValue": ""
				},
				{
					"pinId": "2E37074B47EA52AE3D13B098EF4186AD",
					"name": "then",
					"direction": "Output",
					"type": "exec",
					"defaultValue": ""
				},
				{
					"pinId": "5D57C40647667CE17CBBCFBABB21BCCB",
					"name": "self",
					"direction": "Input",
					"type": "object|/Script/UMG.TextBlock",
					"defaultValue": ""
				},
				{
					"pinId": "7436076846B67C213364E292E0CCFCAA",
					"name": "InText",
					"direction": "Input",
					"type": "text",
					"defaultValue": ""
				}
			]
		},
		{
			"nodeGuid": "C107CC65487AEF6A7A01FA891E8DDDE2",
			"class": "K2Node_VariableGet",
			"title": "Get Img_Selector",
			"comment": "",
			"x": 464,
			"y": 329,
			"memberName": "",
			"functionName": "",
			"variableName": "",
			"targetClass": "",
			"pins": [
				{
					"pinId": "BBC8F45E45EF2284A80BAA82317C3B12",
					"name": "Img_Selector",
					"direction": "Output",
					"type": "object|/Script/UMG.Image",
					"defaultValue": ""
				},
				{
					"pinId": "16DF434048D9F596892FC289FA29BE2A",
					"name": "self",
					"direction": "Input",
					"type": "object|/Game/ChuckContent/UI/WIDGET_MENU/1_MENU_ARCHIVE/Equipment/WBP_SelectorButton.WBP_SelectorButton_C",
					"defaultValue": ""
				}
			]
		},
		{
			"nodeGuid": "DFCDC6824B812D81223831A795EC8B4E",
			"class": "K2Node_VariableGet",
			"title": "Get Txt_Selector",
			"comment": "",
			"x": 128,
			"y": 329,
			"memberName": "",
			"functionName": "",
			"variableName": "",
			"targetClass": "",
			"pins": [
				{
					"pinId": "DCF05D9D4B85700D2CD37EB8E90A7400",
					"name": "Txt_Selector",
					"direction": "Output",
					"type": "object|/Script/UMG.TextBlock",
					"defaultValue": ""
				},
				{
					"pinId": "6B3F1E7940F3631CC22AE2808387835B",
					"name": "self",
					"direction": "Input",
					"type": "object|/Game/ChuckContent/UI/WIDGET_MENU/1_MENU_ARCHIVE/Equipment/WBP_SelectorButton.WBP_SelectorButton_C",
					"defaultValue": ""
				}
			]
		},
		{
			"nodeGuid": "3C64DBD24FC83D8E45832EA23FE6E104",
			"class": "K2Node_VariableGet",
			"title": "Get Icon_Item",
			"comment": "",
			"x": 464,
			"y": 359,
			"memberName": "",
			"functionName": "",
			"variableName": "",
			"targetClass": "",
			"pins": [
				{
					"pinId": "D6C6A7774A3AE7D0074E4E847DCF48A4",
					"name": "Icon_Item",
					"direction": "Output",
					"type": "object|/Script/Engine.Texture2D",
					"defaultValue": ""
				},
				{
					"pinId": "8A8A9D5E47D0DF8344D4F9A249224A06",
					"name": "self",
					"direction": "Input",
					"type": "object|/Game/ChuckContent/UI/WIDGET_MENU/1_MENU_ARCHIVE/Equipment/WBP_SelectorButton.WBP_SelectorButton_C",
					"defaultValue": ""
				}
			]
		},
		{
			"nodeGuid": "B03AC6C74ED971C99CD9F5B3C5BF8C63",
			"class": "K2Node_CallFunction",
			"title": "Set Brush from Texture\nLa destinazione è Immagine",
			"comment": "",
			"x": 624,
			"y": 258,
			"memberName": "",
			"functionName": "",
			"variableName": "",
			"targetClass": "",
			"pins": [
				{
					"pinId": "047FFDF8461D47CD97BAB08FCD15A449",
					"name": "execute",
					"direction": "Input",
					"type": "exec",
					"defaultValue": ""
				},
				{
					"pinId": "AD14EC924A8A5DB8D32FA9A1C6F1827B",
					"name": "then",
					"direction": "Output",
					"type": "exec",
					"defaultValue": ""
				},
				{
					"pinId": "173D8C8F47FEA03D17687791F58986C1",
					"name": "self",
					"direction": "Input",
					"type": "object|/Script/UMG.Image",
					"defaultValue": ""
				},
				{
					"pinId": "5BA1A588492BFD258F87399C84689D7C",
					"name": "Texture",
					"direction": "Input",
					"type": "object|/Script/Engine.Texture2D",
					"defaultValue": ""
				},
				{
					"pinId": "53119EF54B04C6EAFA9922B127E153D0",
					"name": "bMatchSize",
					"direction": "Input",
					"type": "bool",
					"defaultValue": "false"
				}
			]
		},
		{
			"nodeGuid": "21A67B6242EF8244BE3A949A62849606",
			"class": "K2Node_ComponentBoundEvent",
			"title": "On Clicked (Btn_Selector)",
			"comment": "",
			"x": -96,
			"y": 557,
			"memberName": "",
			"functionName": "",
			"variableName": "",
			"targetClass": "",
			"pins": [
				{
					"pinId": "7C569057414B7937F6234BB19E32DC56",
					"name": "OutputDelegate",
					"direction": "Output",
					"type": "delegate",
					"defaultValue": ""
				},
				{
					"pinId": "D1F262ED4ED17A6A3081B39D8ADDC572",
					"name": "then",
					"direction": "Output",
					"type": "exec",
					"defaultValue": ""
				}
			]
		},
		{
			"nodeGuid": "8FC562B644DF473C18CA0DBACDA90DFA",
			"class": "K2Node_CallFunction",
			"title": "Equip and Close\nLa destinazione è WBP Weapon Selector",
			"comment": "",
			"x": 1376,
			"y": 544,
			"memberName": "",
			"functionName": "",
			"variableName": "",
			"targetClass": "",
			"pins": [
				{
					"pinId": "0D185C4E4687B6DF0E28439FB6871528",
					"name": "execute",
					"direction": "Input",
					"type": "exec",
					"defaultValue": ""
				},
				{
					"pinId": "A261A5CB47BFAD05D543D49BFADE631D",
					"name": "then",
					"direction": "Output",
					"type": "exec",
					"defaultValue": ""
				},
				{
					"pinId": "7774752C437482C10A0CA4BC7FBC7327",
					"name": "self",
					"direction": "Input",
					"type": "object|/Game/ChuckContent/UI/WIDGET_MENU/1_MENU_ARCHIVE/Equipment/WBP_WeaponSelector.WBP_WeaponSelector_C",
					"defaultValue": ""
				},
				{
					"pinId": "C4B705B0449E2261FD86019184980F6A",
					"name": "ChosenRow",
					"direction": "Input",
					"type": "name",
					"defaultValue": "None"
				}
			]
		},
		{
			"nodeGuid": "521B960243298641E628EC97C8FA2594",
			"class": "K2Node_VariableGet",
			"title": "Get RowName_Item",
			"comment": "",
			"x": 1216,
			"y": 646,
			"memberName": "",
			"functionName": "",
			"variableName": "",
			"targetClass": "",
			"pins": [
				{
					"pinId": "EF98BA9F41E48C2A405FC4B73AC86040",
					"name": "RowName_Item",
					"direction": "Output",
					"type": "name",
					"defaultValue": "None"
				},
				{
					"pinId": "B5A3B6304EC563DBF67723B803614277",
					"name": "self",
					"direction": "Input",
					"type": "object|/Game/ChuckContent/UI/WIDGET_MENU/1_MENU_ARCHIVE/Equipment/WBP_SelectorButton.WBP_SelectorButton_C",
					"defaultValue": ""
				}
			]
		},
		{
			"nodeGuid": "A4C60D064F287D5D96CE6F8475363884",
			"class": "K2Node_VariableGet",
			"title": "Get ParentSelectorRef",
			"comment": "",
			"x": 1200,
			"y": 616,
			"memberName": "",
			"functionName": "",
			"variableName": "",
			"targetClass": "",
			"pins": [
				{
					"pinId": "1C04704247A5135BBDF7CB999D3F9B92",
					"name": "ParentSelectorRef",
					"direction": "Output",
					"type": "object|/Game/ChuckContent/UI/WIDGET_MENU/1_MENU_ARCHIVE/Equipment/WBP_WeaponSelector.WBP_WeaponSelector_C",
					"defaultValue": ""
				},
				{
					"pinId": "C92EAA724F9EBFE99B4C30ACF9C38B8F",
					"name": "self",
					"direction": "Input",
					"type": "object|/Game/ChuckContent/UI/WIDGET_MENU/1_MENU_ARCHIVE/Equipment/WBP_SelectorButton.WBP_SelectorButton_C",
					"defaultValue": ""
				}
			]
		},
		{
			"nodeGuid": "E71A46EA42C36C4D62C0B98126875B5E",
			"class": "K2Node_MacroInstance",
			"title": "Is Valid",
			"comment": "",
			"x": 960,
			"y": 560,
			"memberName": "",
			"functionName": "",
			"variableName": "",
			"targetClass": "",
			"pins": [
				{
					"pinId": "3650BF1446C5EC401F2E28B7CB3ABB89",
					"name": "exec",
					"direction": "Input",
					"type": "exec",
					"defaultValue": ""
				},
				{
					"pinId": "8D370B9F4ACD7A28D1A520B174C9F26D",
					"name": "InputObject",
					"direction": "Input",
					"type": "object|/Script/CoreUObject.Object",
					"defaultValue": ""
				},
				{
					"pinId": "CF66A44742B81832B77DB0B687EFF5BA",
					"name": "Is Valid",
					"direction": "Output",
					"type": "exec",
					"defaultValue": ""
				},
				{
					"pinId": "0AD1C09D41831B2EE56B3FBBABC70DA4",
					"name": "Is Not Valid",
					"direction": "Output",
					"type": "exec",
					"defaultValue": ""
				}
			]
		},
		{
			"nodeGuid": "EAA5345240E0A0F8503F838C7D7D2063",
			"class": "K2Node_VariableGet",
			"title": "Get ParentSelectorRef",
			"comment": "",
			"x": 992,
			"y": 672,
			"memberName": "",
			"functionName": "",
			"variableName": "",
			"targetClass": "",
			"pins": [
				{
					"pinId": "35D8B36B414AC4A3FA90C0A59277E5AB",
					"name": "ParentSelectorRef",
					"direction": "Output",
					"type": "object|/Game/ChuckContent/UI/WIDGET_MENU/1_MENU_ARCHIVE/Equipment/WBP_WeaponSelector.WBP_WeaponSelector_C",
					"defaultValue": ""
				},
				{
					"pinId": "6F1EDE5A47C48F905868A5B3F9EF7793",
					"name": "self",
					"direction": "Input",
					"type": "object|/Game/ChuckContent/UI/WIDGET_MENU/1_MENU_ARCHIVE/Equipment/WBP_SelectorButton.WBP_SelectorButton_C",
					"defaultValue": ""
				}
			]
		},
		{
			"nodeGuid": "2953842E4498AC5B9812248FC38CC429",
			"class": "K2Node_DynamicCast",
			"title": "Cast To ALS_ChuckBP",
			"comment": "",
			"x": 448,
			"y": 560,
			"memberName": "",
			"functionName": "",
			"variableName": "",
			"targetClass": "",
			"pins": [
				{
					"pinId": "2D09B0A447FCB7F5F9ADE38550510648",
					"name": "execute",
					"direction": "Input",
					"type": "exec",
					"defaultValue": ""
				},
				{
					"pinId": "3908D0104624192AB65BF29AA8604B4F",
					"name": "then",
					"direction": "Output",
					"type": "exec",
					"defaultValue": ""
				},
				{
					"pinId": "509A3E8A470F2FE67A4972A72C44E39D",
					"name": "CastFailed",
					"direction": "Output",
					"type": "exec",
					"defaultValue": ""
				},
				{
					"pinId": "7FD463AA4E33C15F68976AB1DE962B31",
					"name": "Object",
					"direction": "Input",
					"type": "object|/Script/CoreUObject.Object",
					"defaultValue": ""
				},
				{
					"pinId": "BF4C36A84609CE7D8283D99D3F9B5413",
					"name": "AsALS Chuck BP",
					"direction": "Output",
					"type": "object|/Game/ChuckContent/Blueprints/ALS_ChuckBP.ALS_ChuckBP_C",
					"defaultValue": ""
				},
				{
					"pinId": "47037A3E4A2402C5012771A7DBB8780E",
					"name": "bSuccess",
					"direction": "Output",
					"type": "bool",
					"defaultValue": ""
				}
			]
		},
		{
			"nodeGuid": "FC055A3549A22A7ACA1538AB77FF9EAB",
			"class": "K2Node_CallFunction",
			"title": "Commit Equip Item\nLa destinazione è ALS Chuck BP",
			"comment": "",
			"x": 736,
			"y": 544,
			"memberName": "",
			"functionName": "",
			"variableName": "",
			"targetClass": "",
			"pins": [
				{
					"pinId": "F575BBE34FFC4A183FC3DBBC6B2C4E6A",
					"name": "execute",
					"direction": "Input",
					"type": "exec",
					"defaultValue": ""
				},
				{
					"pinId": "63DEAAF24C7CAC6ADCE41DB7C5A45128",
					"name": "then",
					"direction": "Output",
					"type": "exec",
					"defaultValue": ""
				},
				{
					"pinId": "4CFFDC3C46369E80F908B5BB0ECFA6BB",
					"name": "self",
					"direction": "Input",
					"type": "object|/Game/ChuckContent/Blueprints/ALS_ChuckBP.ALS_ChuckBP_C",
					"defaultValue": ""
				},
				{
					"pinId": "3C2D3B03483B6C26466A629AD65B2025",
					"name": "WeaponDataIn",
					"direction": "Input",
					"type": "struct|/Game/ChuckContent/Systems/Weapons/Data/S_WeaponData.S_WeaponData",
					"defaultValue": ""
				},
				{
					"pinId": "4BCC684B4E700A020301F3917D683699",
					"name": "WeaponIndexIn",
					"direction": "Input",
					"type": "int",
					"defaultValue": "0"
				}
			]
		},
		{
			"nodeGuid": "64DD047F4E0330E47AAFA5B8268EF81A",
			"class": "K2Node_CallFunction",
			"title": "Get Player Character",
			"comment": "",
			"x": 432,
			"y": 704,
			"memberName": "",
			"functionName": "",
			"variableName": "",
			"targetClass": "",
			"pins": [
				{
					"pinId": "B0F4F5C24C2AA158509C339D9F0BD69E",
					"name": "self",
					"direction": "Input",
					"type": "object|/Script/Engine.GameplayStatics",
					"defaultValue": "/Script/Engine.Default__GameplayStatics"
				},
				{
					"pinId": "D7C505C84824029BC41C7D8E55DC7626",
					"name": "WorldContextObject",
					"direction": "Input",
					"type": "object|/Script/CoreUObject.Object|const",
					"defaultValue": ""
				},
				{
					"pinId": "723769E84E67E14AFDA6D0AD9C361BE5",
					"name": "PlayerIndex",
					"direction": "Input",
					"type": "int",
					"defaultValue": "0"
				},
				{
					"pinId": "5ACA2D2A43BF21CC398A588565560D59",
					"name": "ReturnValue",
					"direction": "Output",
					"type": "object|/Script/Engine.Character",
					"defaultValue": ""
				}
			]
		},
		{
			"nodeGuid": "90B76D0F42145C6895293B81477E00B9",
			"class": "K2Node_Event",
			"title": "Evento On Added to Focus Path",
			"comment": "",
			"x": 0,
			"y": 976,
			"memberName": "",
			"functionName": "",
			"variableName": "",
			"targetClass": "",
			"pins": [
				{
					"pinId": "5D634E9F456ACF493C113699AB588E82",
					"name": "OutputDelegate",
					"direction": "Output",
					"type": "delegate",
					"defaultValue": ""
				},
				{
					"pinId": "C6B895D140D5FEA4B24DB6B526E283B4",
					"name": "then",
					"direction": "Output",
					"type": "exec",
					"defaultValue": ""
				},
				{
					"pinId": "4C0C769149FC4263E1699F8512ADB9C0",
					"name": "InFocusEvent",
					"direction": "Output",
					"type": "struct|/Script/SlateCore.FocusEvent",
					"defaultValue": ""
				}
			]
		},
		{
			"nodeGuid": "3D457EE5452141D1D92B729E025FB00F",
			"class": "K2Node_Event",
			"title": "Evento On Removed from Focus Path",
			"comment": "",
			"x": 0,
			"y": 1200,
			"memberName": "",
			"functionName": "",
			"variableName": "",
			"targetClass": "",
			"pins": [
				{
					"pinId": "F99BDB06450C01544C8A589D77EDFBE8",
					"name": "OutputDelegate",
					"direction": "Output",
					"type": "delegate",
					"defaultValue": ""
				},
				{
					"pinId": "C2F728E449C5ACD12B3E4B87B0451A72",
					"name": "then",
					"direction": "Output",
					"type": "exec",
					"defaultValue": ""
				},
				{
					"pinId": "5100F3EC465A4D2CFAF2E181389C823B",
					"name": "InFocusEvent",
					"direction": "Output",
					"type": "struct|/Script/SlateCore.FocusEvent",
					"defaultValue": ""
				}
			]
		},
		{
			"nodeGuid": "A094B19E462D68732C4877B4F9D5851D",
			"class": "K2Node_VariableGet",
			"title": "Get Btn_Selector",
			"comment": "",
			"x": 320,
			"y": 1032,
			"memberName": "",
			"functionName": "",
			"variableName": "",
			"targetClass": "",
			"pins": [
				{
					"pinId": "AE15A5AD494B0420D4F7998D93A5FE5D",
					"name": "Btn_Selector",
					"direction": "Output",
					"type": "object|/Script/UMG.Button",
					"defaultValue": ""
				},
				{
					"pinId": "84443BBC4E7132BF70190C86AAC250CC",
					"name": "self",
					"direction": "Input",
					"type": "object|/Game/ChuckContent/UI/WIDGET_MENU/1_MENU_ARCHIVE/Equipment/WBP_SelectorButton.WBP_SelectorButton_C",
					"defaultValue": ""
				}
			]
		},
		{
			"nodeGuid": "2F74D0024F6C547476E496AEF43AA89E",
			"class": "K2Node_VariableGet",
			"title": "Get Btn_Selector",
			"comment": "",
			"x": 304,
			"y": 1256,
			"memberName": "",
			"functionName": "",
			"variableName": "",
			"targetClass": "",
			"pins": [
				{
					"pinId": "D1839FCC43C1963C45F6EAAE23FBED63",
					"name": "Btn_Selector",
					"direction": "Output",
					"type": "object|/Script/UMG.Button",
					"defaultValue": ""
				},
				{
					"pinId": "03E8573944826CFD2B92C394F7EB3CED",
					"name": "self",
					"direction": "Input",
					"type": "object|/Game/ChuckContent/UI/WIDGET_MENU/1_MENU_ARCHIVE/Equipment/WBP_SelectorButton.WBP_SelectorButton_C",
					"defaultValue": ""
				}
			]
		},
		{
			"nodeGuid": "A8FEA6894A7637FC421570BE511430E5",
			"class": "K2Node_CallFunction",
			"title": "Set Background Color\nLa destinazione è Pulsante",
			"comment": "",
			"x": 464,
			"y": 1184,
			"memberName": "",
			"functionName": "",
			"variableName": "",
			"targetClass": "",
			"pins": [
				{
					"pinId": "6EF0CF1E46DDA60C9F8C218D4D3B096F",
					"name": "execute",
					"direction": "Input",
					"type": "exec",
					"defaultValue": ""
				},
				{
					"pinId": "D8724AFA434F10542817139AD9D8550B",
					"name": "then",
					"direction": "Output",
					"type": "exec",
					"defaultValue": ""
				},
				{
					"pinId": "DB1C8B5A4C60AC08B7002F85C6FF5569",
					"name": "self",
					"direction": "Input",
					"type": "object|/Script/UMG.Button",
					"defaultValue": ""
				},
				{
					"pinId": "E77F72FB438FD64D2D5550B7CD70B411",
					"name": "InBackgroundColor",
					"direction": "Input",
					"type": "struct|/Script/CoreUObject.LinearColor",
					"defaultValue": "(R=0.093059,G=0.093059,B=0.093059,A=0.501961)"
				}
			]
		},
		{
			"nodeGuid": "7C765F8D4FB43CC6373D728B15D74D00",
			"class": "K2Node_CallFunction",
			"title": "Set Background Color\nLa destinazione è Pulsante",
			"comment": "",
			"x": 464,
			"y": 960,
			"memberName": "",
			"functionName": "",
			"variableName": "",
			"targetClass": "",
			"pins": [
				{
					"pinId": "6DE4BB5A4804DB5EEFAEDBB3717D3A01",
					"name": "execute",
					"direction": "Input",
					"type": "exec",
					"defaultValue": ""
				},
				{
					"pinId": "7E0E098E412413F26A200183B15C513B",
					"name": "then",
					"direction": "Output",
					"type": "exec",
					"defaultValue": ""
				},
				{
					"pinId": "9EA0D7A143FE868C69B71ABE5EB79032",
					"name": "self",
					"direction": "Input",
					"type": "object|/Script/UMG.Button",
					"defaultValue": ""
				},
				{
					"pinId": "BD1867C04D0938A4E7020CBCB8B6B761",
					"name": "InBackgroundColor",
					"direction": "Input",
					"type": "struct|/Script/CoreUObject.LinearColor",
					"defaultValue": "(R=1.000000,G=1.000000,B=1.000000,A=0.501961)"
				}
			]
		},
		{
			"nodeGuid": "404E523A42788637E69C11BF1F5029B6",
			"class": "K2Node_CallFunction",
			"title": "Play Sound 2D",
			"comment": "",
			"x": 160,
			"y": 560,
			"memberName": "",
			"functionName": "",
			"variableName": "",
			"targetClass": "",
			"pins": [
				{
					"pinId": "A4346E6145A5240CE123B78018A1BAE2",
					"name": "execute",
					"direction": "Input",
					"type": "exec",
					"defaultValue": ""
				},
				{
					"pinId": "2E22D6EC4588DEA6171D25838A669B6C",
					"name": "then",
					"direction": "Output",
					"type": "exec",
					"defaultValue": ""
				},
				{
					"pinId": "DDC3B7B640233FE53EBD8B961054FD44",
					"name": "self",
					"direction": "Input",
					"type": "object|/Script/Engine.GameplayStatics",
					"defaultValue": "/Script/Engine.Default__GameplayStatics"
				},
				{
					"pinId": "2986A2FB4A04E65E0C05C5B26A114D51",
					"name": "WorldContextObject",
					"direction": "Input",
					"type": "object|/Script/CoreUObject.Object|const",
					"defaultValue": ""
				},
				{
					"pinId": "9F5CCDDF4D8F7211C9839DBC99C9F325",
					"name": "Sound",
					"direction": "Input",
					"type": "object|/Script/Engine.SoundBase",
					"defaultValue": "/Game/AdditionalContents/_WeaponsPacks/MilitaryWeapDark/Sound/Rifle/Wavs/Rifle_Reload01.Rifle_Reload01"
				},
				{
					"pinId": "BFE026EF442BF9D076C6D8B71675837E",
					"name": "VolumeMultiplier",
					"direction": "Input",
					"type": "real|float",
					"defaultValue": "1.000000"
				},
				{
					"pinId": "10DEEC4F42F02B3DA08076A71D36F878",
					"name": "PitchMultiplier",
					"direction": "Input",
					"type": "real|float",
					"defaultValue": "1.000000"
				},
				{
					"pinId": "7C019FEF437706D5003DBB9E19C97E36",
					"name": "StartTime",
					"direction": "Input",
					"type": "real|float",
					"defaultValue": "0.000000"
				},
				{
					"pinId": "CF7EAAB94CC18E241C406CB2B35AB496",
					"name": "ConcurrencySettings",
					"direction": "Input",
					"type": "object|/Script/Engine.SoundConcurrency",
					"defaultValue": ""
				},
				{
					"pinId": "77E1680045BBDD87E7C744BADB2BA2FF",
					"name": "OwningActor",
					"direction": "Input",
					"type": "object|/Script/Engine.Actor|const",
					"defaultValue": ""
				},
				{
					"pinId": "DFC7ED064BC58CFF3AAF9F99F5349D1D",
					"name": "bIsUISound",
					"direction": "Input",
					"type": "bool",
					"defaultValue": "true"
				}
			]
		},
		{
			"nodeGuid": "0AE0E4C3492C74F75D26788D1E670A97",
			"class": "K2Node_VariableGet",
			"title": "Get WeaponData",
			"comment": "",
			"x": 768,
			"y": 736,
			"memberName": "",
			"functionName": "",
			"variableName": "",
			"targetClass": "",
			"pins": [
				{
					"pinId": "9A324BDE4735A09A55A112802CAD4ED5",
					"name": "WeaponData",
					"direction": "Output",
					"type": "struct|/Game/ChuckContent/Systems/Weapons/Data/S_WeaponData.S_WeaponData",
					"defaultValue": ""
				},
				{
					"pinId": "00E088C94D70180BB47B90B8F1636850",
					"name": "self",
					"direction": "Input",
					"type": "object|/Game/ChuckContent/UI/WIDGET_MENU/1_MENU_ARCHIVE/Equipment/WBP_SelectorButton.WBP_SelectorButton_C",
					"defaultValue": ""
				}
			]
		},
		{
			"nodeGuid": "C3E4F8B64180DFC7B0539BB375E5FE9A",
			"class": "K2Node_VariableGet",
			"title": "Get WeaponIndex",
			"comment": "",
			"x": 768,
			"y": 768,
			"memberName": "",
			"functionName": "",
			"variableName": "",
			"targetClass": "",
			"pins": [
				{
					"pinId": "5DDB9E48494C82ACFC1B3BBC22F4DD8A",
					"name": "WeaponIndex",
					"direction": "Output",
					"type": "int",
					"defaultValue": "0"
				},
				{
					"pinId": "BD3B3D6A4582D739D0E70B97D08C3C6E",
					"name": "self",
					"direction": "Input",
					"type": "object|/Game/ChuckContent/UI/WIDGET_MENU/1_MENU_ARCHIVE/Equipment/WBP_SelectorButton.WBP_SelectorButton_C",
					"defaultValue": ""
				}
			]
		}
	],
	"edges": [
		{
			"assetKey": "Game_ChuckContent_UI_WIDGET_MENU_1_MENU_ARCHIVE_Equipment_WBP_SelectorButton",
			"graph": "EventGraph",
			"edgeType": "exec",
			"fromNodeGuid": "9A1F535A4C046FC809050A87C2BB6C4D",
			"fromPinId": "37BB92294B2E6EC6DB85D1BC7E7D69A4",
			"fromPinName": "then",
			"toNodeGuid": "02EDC53B461F614D5C04E98FA83BB160",
			"toPinId": "03406C0F480FE622A4F78480951934A8",
			"toPinName": "execute"
		},
		{
			"assetKey": "Game_ChuckContent_UI_WIDGET_MENU_1_MENU_ARCHIVE_Equipment_WBP_SelectorButton",
			"graph": "EventGraph",
			"edgeType": "data",
			"fromNodeGuid": "678F9A75450022669630FBBAB239A734",
			"fromPinId": "CF50978A4B4ED96D02057C88C8D02509",
			"fromPinName": "Txt_ItemName",
			"toNodeGuid": "02EDC53B461F614D5C04E98FA83BB160",
			"toPinId": "7436076846B67C213364E292E0CCFCAA",
			"toPinName": "InText"
		},
		{
			"assetKey": "Game_ChuckContent_UI_WIDGET_MENU_1_MENU_ARCHIVE_Equipment_WBP_SelectorButton",
			"graph": "EventGraph",
			"edgeType": "exec",
			"fromNodeGuid": "02EDC53B461F614D5C04E98FA83BB160",
			"fromPinId": "2E37074B47EA52AE3D13B098EF4186AD",
			"fromPinName": "then",
			"toNodeGuid": "B03AC6C74ED971C99CD9F5B3C5BF8C63",
			"toPinId": "047FFDF8461D47CD97BAB08FCD15A449",
			"toPinName": "execute"
		},
		{
			"assetKey": "Game_ChuckContent_UI_WIDGET_MENU_1_MENU_ARCHIVE_Equipment_WBP_SelectorButton",
			"graph": "EventGraph",
			"edgeType": "data",
			"fromNodeGuid": "DFCDC6824B812D81223831A795EC8B4E",
			"fromPinId": "DCF05D9D4B85700D2CD37EB8E90A7400",
			"fromPinName": "Txt_Selector",
			"toNodeGuid": "02EDC53B461F614D5C04E98FA83BB160",
			"toPinId": "5D57C40647667CE17CBBCFBABB21BCCB",
			"toPinName": "self"
		},
		{
			"assetKey": "Game_ChuckContent_UI_WIDGET_MENU_1_MENU_ARCHIVE_Equipment_WBP_SelectorButton",
			"graph": "EventGraph",
			"edgeType": "data",
			"fromNodeGuid": "C107CC65487AEF6A7A01FA891E8DDDE2",
			"fromPinId": "BBC8F45E45EF2284A80BAA82317C3B12",
			"fromPinName": "Img_Selector",
			"toNodeGuid": "B03AC6C74ED971C99CD9F5B3C5BF8C63",
			"toPinId": "173D8C8F47FEA03D17687791F58986C1",
			"toPinName": "self"
		},
		{
			"assetKey": "Game_ChuckContent_UI_WIDGET_MENU_1_MENU_ARCHIVE_Equipment_WBP_SelectorButton",
			"graph": "EventGraph",
			"edgeType": "data",
			"fromNodeGuid": "3C64DBD24FC83D8E45832EA23FE6E104",
			"fromPinId": "D6C6A7774A3AE7D0074E4E847DCF48A4",
			"fromPinName": "Icon_Item",
			"toNodeGuid": "B03AC6C74ED971C99CD9F5B3C5BF8C63",
			"toPinId": "5BA1A588492BFD258F87399C84689D7C",
			"toPinName": "Texture"
		},
		{
			"assetKey": "Game_ChuckContent_UI_WIDGET_MENU_1_MENU_ARCHIVE_Equipment_WBP_SelectorButton",
			"graph": "EventGraph",
			"edgeType": "exec",
			"fromNodeGuid": "21A67B6242EF8244BE3A949A62849606",
			"fromPinId": "D1F262ED4ED17A6A3081B39D8ADDC572",
			"fromPinName": "then",
			"toNodeGuid": "404E523A42788637E69C11BF1F5029B6",
			"toPinId": "A4346E6145A5240CE123B78018A1BAE2",
			"toPinName": "execute"
		},
		{
			"assetKey": "Game_ChuckContent_UI_WIDGET_MENU_1_MENU_ARCHIVE_Equipment_WBP_SelectorButton",
			"graph": "EventGraph",
			"edgeType": "exec",
			"fromNodeGuid": "E71A46EA42C36C4D62C0B98126875B5E",
			"fromPinId": "CF66A44742B81832B77DB0B687EFF5BA",
			"fromPinName": "Is Valid",
			"toNodeGuid": "8FC562B644DF473C18CA0DBACDA90DFA",
			"toPinId": "0D185C4E4687B6DF0E28439FB6871528",
			"toPinName": "execute"
		},
		{
			"assetKey": "Game_ChuckContent_UI_WIDGET_MENU_1_MENU_ARCHIVE_Equipment_WBP_SelectorButton",
			"graph": "EventGraph",
			"edgeType": "data",
			"fromNodeGuid": "A4C60D064F287D5D96CE6F8475363884",
			"fromPinId": "1C04704247A5135BBDF7CB999D3F9B92",
			"fromPinName": "ParentSelectorRef",
			"toNodeGuid": "8FC562B644DF473C18CA0DBACDA90DFA",
			"toPinId": "7774752C437482C10A0CA4BC7FBC7327",
			"toPinName": "self"
		},
		{
			"assetKey": "Game_ChuckContent_UI_WIDGET_MENU_1_MENU_ARCHIVE_Equipment_WBP_SelectorButton",
			"graph": "EventGraph",
			"edgeType": "data",
			"fromNodeGuid": "521B960243298641E628EC97C8FA2594",
			"fromPinId": "EF98BA9F41E48C2A405FC4B73AC86040",
			"fromPinName": "RowName_Item",
			"toNodeGuid": "8FC562B644DF473C18CA0DBACDA90DFA",
			"toPinId": "C4B705B0449E2261FD86019184980F6A",
			"toPinName": "ChosenRow"
		},
		{
			"assetKey": "Game_ChuckContent_UI_WIDGET_MENU_1_MENU_ARCHIVE_Equipment_WBP_SelectorButton",
			"graph": "EventGraph",
			"edgeType": "exec",
			"fromNodeGuid": "FC055A3549A22A7ACA1538AB77FF9EAB",
			"fromPinId": "63DEAAF24C7CAC6ADCE41DB7C5A45128",
			"fromPinName": "then",
			"toNodeGuid": "E71A46EA42C36C4D62C0B98126875B5E",
			"toPinId": "3650BF1446C5EC401F2E28B7CB3ABB89",
			"toPinName": "exec"
		},
		{
			"assetKey": "Game_ChuckContent_UI_WIDGET_MENU_1_MENU_ARCHIVE_Equipment_WBP_SelectorButton",
			"graph": "EventGraph",
			"edgeType": "data",
			"fromNodeGuid": "EAA5345240E0A0F8503F838C7D7D2063",
			"fromPinId": "35D8B36B414AC4A3FA90C0A59277E5AB",
			"fromPinName": "ParentSelectorRef",
			"toNodeGuid": "E71A46EA42C36C4D62C0B98126875B5E",
			"toPinId": "8D370B9F4ACD7A28D1A520B174C9F26D",
			"toPinName": "InputObject"
		},
		{
			"assetKey": "Game_ChuckContent_UI_WIDGET_MENU_1_MENU_ARCHIVE_Equipment_WBP_SelectorButton",
			"graph": "EventGraph",
			"edgeType": "exec",
			"fromNodeGuid": "404E523A42788637E69C11BF1F5029B6",
			"fromPinId": "2E22D6EC4588DEA6171D25838A669B6C",
			"fromPinName": "then",
			"toNodeGuid": "2953842E4498AC5B9812248FC38CC429",
			"toPinId": "2D09B0A447FCB7F5F9ADE38550510648",
			"toPinName": "execute"
		},
		{
			"assetKey": "Game_ChuckContent_UI_WIDGET_MENU_1_MENU_ARCHIVE_Equipment_WBP_SelectorButton",
			"graph": "EventGraph",
			"edgeType": "exec",
			"fromNodeGuid": "2953842E4498AC5B9812248FC38CC429",
			"fromPinId": "3908D0104624192AB65BF29AA8604B4F",
			"fromPinName": "then",
			"toNodeGuid": "FC055A3549A22A7ACA1538AB77FF9EAB",
			"toPinId": "F575BBE34FFC4A183FC3DBBC6B2C4E6A",
			"toPinName": "execute"
		},
		{
			"assetKey": "Game_ChuckContent_UI_WIDGET_MENU_1_MENU_ARCHIVE_Equipment_WBP_SelectorButton",
			"graph": "EventGraph",
			"edgeType": "data",
			"fromNodeGuid": "64DD047F4E0330E47AAFA5B8268EF81A",
			"fromPinId": "5ACA2D2A43BF21CC398A588565560D59",
			"fromPinName": "ReturnValue",
			"toNodeGuid": "2953842E4498AC5B9812248FC38CC429",
			"toPinId": "7FD463AA4E33C15F68976AB1DE962B31",
			"toPinName": "Object"
		},
		{
			"assetKey": "Game_ChuckContent_UI_WIDGET_MENU_1_MENU_ARCHIVE_Equipment_WBP_SelectorButton",
			"graph": "EventGraph",
			"edgeType": "data",
			"fromNodeGuid": "2953842E4498AC5B9812248FC38CC429",
			"fromPinId": "BF4C36A84609CE7D8283D99D3F9B5413",
			"fromPinName": "AsALS Chuck BP",
			"toNodeGuid": "FC055A3549A22A7ACA1538AB77FF9EAB",
			"toPinId": "4CFFDC3C46369E80F908B5BB0ECFA6BB",
			"toPinName": "self"
		},
		{
			"assetKey": "Game_ChuckContent_UI_WIDGET_MENU_1_MENU_ARCHIVE_Equipment_WBP_SelectorButton",
			"graph": "EventGraph",
			"edgeType": "data",
			"fromNodeGuid": "0AE0E4C3492C74F75D26788D1E670A97",
			"fromPinId": "9A324BDE4735A09A55A112802CAD4ED5",
			"fromPinName": "WeaponData",
			"toNodeGuid": "FC055A3549A22A7ACA1538AB77FF9EAB",
			"toPinId": "3C2D3B03483B6C26466A629AD65B2025",
			"toPinName": "WeaponDataIn"
		},
		{
			"assetKey": "Game_ChuckContent_UI_WIDGET_MENU_1_MENU_ARCHIVE_Equipment_WBP_SelectorButton",
			"graph": "EventGraph",
			"edgeType": "data",
			"fromNodeGuid": "C3E4F8B64180DFC7B0539BB375E5FE9A",
			"fromPinId": "5DDB9E48494C82ACFC1B3BBC22F4DD8A",
			"fromPinName": "WeaponIndex",
			"toNodeGuid": "FC055A3549A22A7ACA1538AB77FF9EAB",
			"toPinId": "4BCC684B4E700A020301F3917D683699",
			"toPinName": "WeaponIndexIn"
		},
		{
			"assetKey": "Game_ChuckContent_UI_WIDGET_MENU_1_MENU_ARCHIVE_Equipment_WBP_SelectorButton",
			"graph": "EventGraph",
			"edgeType": "exec",
			"fromNodeGuid": "90B76D0F42145C6895293B81477E00B9",
			"fromPinId": "C6B895D140D5FEA4B24DB6B526E283B4",
			"fromPinName": "then",
			"toNodeGuid": "7C765F8D4FB43CC6373D728B15D74D00",
			"toPinId": "6DE4BB5A4804DB5EEFAEDBB3717D3A01",
			"toPinName": "execute"
		},
		{
			"assetKey": "Game_ChuckContent_UI_WIDGET_MENU_1_MENU_ARCHIVE_Equipment_WBP_SelectorButton",
			"graph": "EventGraph",
			"edgeType": "exec",
			"fromNodeGuid": "3D457EE5452141D1D92B729E025FB00F",
			"fromPinId": "C2F728E449C5ACD12B3E4B87B0451A72",
			"fromPinName": "then",
			"toNodeGuid": "A8FEA6894A7637FC421570BE511430E5",
			"toPinId": "6EF0CF1E46DDA60C9F8C218D4D3B096F",
			"toPinName": "execute"
		},
		{
			"assetKey": "Game_ChuckContent_UI_WIDGET_MENU_1_MENU_ARCHIVE_Equipment_WBP_SelectorButton",
			"graph": "EventGraph",
			"edgeType": "data",
			"fromNodeGuid": "A094B19E462D68732C4877B4F9D5851D",
			"fromPinId": "AE15A5AD494B0420D4F7998D93A5FE5D",
			"fromPinName": "Btn_Selector",
			"toNodeGuid": "7C765F8D4FB43CC6373D728B15D74D00",
			"toPinId": "9EA0D7A143FE868C69B71ABE5EB79032",
			"toPinName": "self"
		},
		{
			"assetKey": "Game_ChuckContent_UI_WIDGET_MENU_1_MENU_ARCHIVE_Equipment_WBP_SelectorButton",
			"graph": "EventGraph",
			"edgeType": "data",
			"fromNodeGuid": "2F74D0024F6C547476E496AEF43AA89E",
			"fromPinId": "D1839FCC43C1963C45F6EAAE23FBED63",
			"fromPinName": "Btn_Selector",
			"toNodeGuid": "A8FEA6894A7637FC421570BE511430E5",
			"toPinId": "DB1C8B5A4C60AC08B7002F85C6FF5569",
			"toPinName": "self"
		}
	],
	"variablesRead": [
		"Get Btn_Selector",
		"Get Icon_Item",
		"Get Img_Selector",
		"Get ParentSelectorRef",
		"Get RowName_Item",
		"Get Txt_ItemName",
		"Get Txt_Selector",
		"Get WeaponData",
		"Get WeaponIndex"
	],
	"variablesWritten": [],
	"functionsCalled": [
		"Commit Equip Item\nLa destinazione è ALS Chuck BP",
		"Equip and Close\nLa destinazione è WBP Weapon Selector",
		"Get Player Character",
		"Play Sound 2D",
		"Set Background Color\nLa destinazione è Pulsante",
		"Set Brush from Texture\nLa destinazione è Immagine",
		"SetText (Text)\nLa destinazione è Testo"
	],
	"widgetsTouched": [
		"Set Brush from Texture\nLa destinazione è Immagine",
		"SetText (Text)\nLa destinazione è Testo"
	],
	"componentsTouched": [
		"On Clicked (Btn_Selector)"
	],
	"externalBlueprintReferences": [
		"Cast To ALS_ChuckBP",
		"Commit Equip Item\nLa destinazione è ALS Chuck BP",
		"Equip and Close\nLa destinazione è WBP Weapon Selector",
		"Get Player Character",
		"Play Sound 2D",
		"Set Background Color\nLa destinazione è Pulsante",
		"Set Brush from Texture\nLa destinazione è Immagine",
		"SetText (Text)\nLa destinazione è Testo"
	],
	"flowId": "F003",
	"graphId": "G001",
	"assetName": "WBP_SelectorButton",
	"assetPath": "/Game/ChuckContent/UI/WIDGET_MENU/1_MENU_ARCHIVE/Equipment/WBP_SelectorButton.WBP_SelectorButton"
}